malwarebazaar/__init__.py
malwarebazaar/api/__init__.py
malwarebazaar/api/bazaar.py
malwarebazaar/api/yaraify.py
malwarebazaar/bazaar.py
malwarebazaar/config.py
malwarebazaar/models.py
malwarebazaar/output.py
malwarebazaar/platform.py
malwarebazaar/py.typed
malwarebazaar/util.py
malwarebazaar/yaraify.py
malwarebazaar-0.2.8.dist-info/LICENSE
malwarebazaar-0.2.8.dist-info/METADATA
malwarebazaar-0.2.8.dist-info/WHEEL
malwarebazaar-0.2.8.dist-info/entry_points.txt
malwarebazaar-0.2.8.dist-info/RECORD
