Metadata-Version: 2.3
Name: malwarebazaar
Version: 0.2.8
Summary: CLI wrapper for malware bazaar API (bazaar.abuse.ch) and YARAify API (yaraify.abuse.ch)
License: MIT
Author: 3c7
Author-email: 3c7@posteo.de
Requires-Python: >=3.9,<3.14
Classifier: Development Status :: 5 - Production/Stable
Classifier: License :: OSI Approved :: MIT License
Classifier: Programming Language :: Python :: 3
Classifier: Programming Language :: Python :: 3.9
Classifier: Programming Language :: Python :: 3.10
Classifier: Programming Language :: Python :: 3.11
Classifier: Programming Language :: Python :: 3.12
Classifier: Programming Language :: Python :: 3.13
Classifier: Programming Language :: Python :: 3 :: Only
Classifier: Topic :: Security
Provides-Extra: cli
Requires-Dist: PyYAML (>=6.0.1,<7.0.0)
Requires-Dist: pydantic (>=2.4.2,<3.0.0)
Requires-Dist: pyzipper (>=0.3.6,<0.4.0)
Requires-Dist: requests (>=2.31.0,<3.0.0)
Requires-Dist: rich (>=13.6.0,<14.0.0) ; extra == "cli"
Requires-Dist: typer (>=0.9.0,<0.10.0) ; extra == "cli"
Project-URL: Homepage, https://github.com/3c7/bazaar
Project-URL: Repository, https://github.com/3c7/bazaar
